parody_mcp/__init__.py
parody_mcp/tool.py
parody_mcp-0.1.1.dist-info/LICENSE
parody_mcp-0.1.1.dist-info/METADATA
parody_mcp-0.1.1.dist-info/WHEEL
parody_mcp-0.1.1.dist-info/entry_points.txt
parody_mcp-0.1.1.dist-info/top_level.txt
parody_mcp-0.1.1.dist-info/RECORD
