Metadata-Version: 2.2
Name: parody-mcp
Version: 0.1.1
Summary: An MCP tool that suggests funny, phonetically similar words
Author-email: Patrick Ruff <patruff@gmail.com>
License: MIT
Requires-Python: <3.12,>=3.8
License-File: LICENSE
Requires-Dist: mcp>=0.1.0
Requires-Dist: mcpadapt>=0.1.0
Requires-Dist: anyio>=4.0.0
Requires-Dist: smolagents>=0.1.0
Requires-Dist: pronouncing>=0.2.0
Provides-Extra: dev
Requires-Dist: pytest>=7.0; extra == "dev"
Requires-Dist: black>=22.0; extra == "dev"
